fast_pyworld3/__init__.py
fast_pyworld3/core.py
fast_pyworld3/data/functions_table_world3.json
fast_pyworld3/sectors/__init__.py
fast_pyworld3/sectors/agriculture.py
fast_pyworld3/sectors/base.py
fast_pyworld3/sectors/capital.py
fast_pyworld3/sectors/pollution.py
fast_pyworld3/sectors/population.py
fast_pyworld3/sectors/resource.py
fast_pyworld3/utils/__init__.py
fast_pyworld3/utils/delays.py
fast_pyworld3/utils/functions.py
fast_pyworld3-1.0.0.dist-info/WHEEL
fast_pyworld3-1.0.0.dist-info/METADATA
fast_pyworld3-1.0.0.dist-info/RECORD
