Metadata-Version: 2.4
Name: fast_pyworld3
Version: 1.0.0
Summary: A high-performance Python implementation of the World3 model from Limits to Growth (2004). 20x faster than PyWorld3-03.
Keywords: world3,limits-to-growth,simulation,system-dynamics,modeling
Author: who care
License-Expression: CECILL-2.1
Classifier: Development Status :: 4 - Beta
Classifier: Intended Audience :: Science/Research
Classifier: License :: OSI Approved :: CEA CNRS Inria Logiciel Libre License, version 2.1 (CeCILL-2.1)
Classifier: Programming Language :: Python :: 3
Classifier: Programming Language :: Python :: 3.13
Classifier: Topic :: Scientific/Engineering
Classifier: Topic :: Scientific/Engineering :: Mathematics
Requires-Dist: numpy>=2.4.0
Requires-Dist: scipy>=1.16.3
Requires-Dist: matplotlib>=3.10.8
Requires-Dist: pytest>=9.0.0 ; extra == 'dev'
Requires-Dist: basedpyright>=1.37.0 ; extra == 'dev'
Requires-Dist: ruff>=0.14.10 ; extra == 'dev'
Requires-Python: >=3.13
Project-URL: Documentation, https://github.com/fast_pyworld3/fast_pyworld3#readme
Project-URL: Homepage, https://github.com/fast_pyworld3/fast_pyworld3
Provides-Extra: dev
